indico_prometheus/__init__.py
indico_prometheus/blueprint.py
indico_prometheus/controllers.py
indico_prometheus/metrics.py
indico_prometheus/plugin.py
indico_prometheus/queries.py
indico_plugin_prometheus-3.3.2.dist-info/METADATA
indico_plugin_prometheus-3.3.2.dist-info/WHEEL
indico_plugin_prometheus-3.3.2.dist-info/entry_points.txt
indico_plugin_prometheus-3.3.2.dist-info/RECORD
