Metadata-Version: 2.4
Name: indico-plugin-prometheus
Version: 3.3.2
Summary: Prometheus metrics in Indico servers
Project-URL: GitHub, https://github.com/indico/indico-plugins
Author-email: Indico Team <indico-team@cern.ch>
License-Expression: MIT
Classifier: Environment :: Plugins
Classifier: Environment :: Web Environment
Classifier: License :: OSI Approved :: MIT License
Classifier: Programming Language :: Python :: 3.12
Requires-Python: <3.13,>=3.12.2
Requires-Dist: indico>=3.3
Requires-Dist: prometheus-client==0.22.1
